tercontrol.cpython-38-x86_64-linux-gnu.so
libs/terminfo.cpython-38-x86_64-linux-gnu.so
tercontrol-1.0.5.dist-info/METADATA
tercontrol-1.0.5.dist-info/RECORD
tercontrol-1.0.5.dist-info/WHEEL
tercontrol-1.0.5.dist-info/LICENSE
tercontrol-1.0.5.dist-info/top_level.txt
