Metadata-Version: 2.1
Name: tercontrol
Version: 1.0.5
Summary: Lightweight POSIX terminal control library for python3
Home-page: UNKNOWN
Author: Zackery .R. Smith
Author-email: UNKNOWN
License: UNKNOWN
Platform: UNKNOWN
Requires-Dist: PyGObject ; platform_system == "Linux"
